as_shinchan/__init__.py
as_shinchan-1.0.0.dist-info/LICENSE
as_shinchan-1.0.0.dist-info/METADATA
as_shinchan-1.0.0.dist-info/WHEEL
as_shinchan-1.0.0.dist-info/top_level.txt
as_shinchan-1.0.0.dist-info/RECORD
